pinakin/__init__.py
pinakin/ravan.py
pinakin/upstox.py
pinakin-0.2.dist-info/LICENSE
pinakin-0.2.dist-info/METADATA
pinakin-0.2.dist-info/WHEEL
pinakin-0.2.dist-info/top_level.txt
pinakin-0.2.dist-info/RECORD
