Metadata-Version: 2.1
Name: pinakin
Version: 0.2
Summary: Unofficial Python Wrapper library for Upstox
Home-page: https://unofficed.com
Author: Aeron7
Author-email: dexter@unofficed.com
Keywords: upstox,uplink,python,nse,trading,stock markets
Classifier: Intended Audience :: Developers
Classifier: Natural Language :: English
Classifier: Operating System :: OS Independent
Classifier: Programming Language :: Python
Classifier: Programming Language :: Python :: 3
Classifier: Programming Language :: Python :: Implementation :: PyPy
Classifier: Topic :: Software Development :: Libraries :: Python Modules
License-File: LICENSE
Requires-Dist: requests
Requires-Dist: pandas
Requires-Dist: curlify
